bisturi/__init__.py
bisturi/blocks.py
bisturi/deferred.py
bisturi/descriptor.py
bisturi/field.py
bisturi/fragments.py
bisturi/packet.py
bisturi/packet_builder.py
bisturi/pattern_matching.py
bisturi/six.py
bisturi/structural_fields.py
bisturi/util.py
bisturi-0.5.0.dist-info/DESCRIPTION.rst
bisturi-0.5.0.dist-info/METADATA
bisturi-0.5.0.dist-info/RECORD
bisturi-0.5.0.dist-info/WHEEL
bisturi-0.5.0.dist-info/metadata.json
bisturi-0.5.0.dist-info/top_level.txt
