Metadata-Version: 1.2
Name: bisturi
Version: 0.5.0
Summary: Parse binary data painless describing the packets' structures in python classes: no need to write 'for' loops or nested 'if' conditionals.
Home-page: https://github.com/gehnch/bisturi
Author: Gehn
Author-email: use-github-issues@example.com
License: GNU LGPLv3
Keywords: parse parsing binary network file compiler code generator
Platform: UNKNOWN
Classifier: Development Status :: 4 - Beta
Classifier: Intended Audience :: Developers
Classifier: License :: OSI Approved :: GNU Lesser General Public License v3 (LGPLv3)
Classifier: Programming Language :: Python :: 2
Classifier: Programming Language :: Python :: 3
Classifier: Topic :: Software Development :: Code Generators
Classifier: Topic :: Software Development :: Compilers
Classifier: Topic :: Software Development :: Libraries :: Python Modules
Requires-Python: >=2.6
